lop_codeingame_cli/__init__.py
lop_codeingame_cli/command/__init__.py
lop_codeingame_cli/command/lopauth.py
lop_codeingame_cli/command/lopdownload.py
lop_codeingame_cli/command/lopgenerate.py
lop_codeingame_cli/command/lopsubmit.py
lop_codeingame_cli/enumerations/__init__.py
lop_codeingame_cli/enumerations/main.py
lop_codeingame_cli/generator/__init__.py
lop_codeingame_cli/generator/base.py
lop_codeingame_cli/generator/python.py
lop_codeingame_cli/model/__init__.py
lop_codeingame_cli/model/Exercise.py
lop_codeingame_cli/utilities/__init__.py
lop_codeingame_cli/utilities/file.py
lop_codeingame_cli/utilities/request.py
lop_codeingame_cli/utilities/variables.py
lop_codeingame_cli-0.1.6.dist-info/entry_points.txt
lop_codeingame_cli-0.1.6.dist-info/METADATA
lop_codeingame_cli-0.1.6.dist-info/WHEEL
lop_codeingame_cli-0.1.6.dist-info/RECORD
