Metadata-Version: 2.1
Name: lop-codeingame-cli
Version: 0.1.6
Summary: 
License: MIT
Author: machkouroke
Author-email: machkour20.mo1@gmail.com
Requires-Python: >=3.10,<4.0
Classifier: License :: OSI Approved :: MIT License
Classifier: Programming Language :: Python :: 3
Classifier: Programming Language :: Python :: 3.10
Classifier: Programming Language :: Python :: 3.11
Requires-Dist: clint (>=0.5.1,<0.6.0)
Requires-Dist: pydantic (>=1.10.8,<2.0.0)
Requires-Dist: pyyaml (>=6.0,<7.0)
Requires-Dist: requests (>=2.31.0,<3.0.0)
Requires-Dist: tqdm (>=4.65.0,<5.0.0)
Requires-Dist: typer (>=0.9.0,<0.10.0)
Requires-Dist: websocket-client (>=1.5.2,<2.0.0)
